octodeco/__init__.py
octodeco/deco/Buhlmann.py
octodeco/deco/BuhlmannConstants.py
octodeco/deco/CNSConstants.py
octodeco/deco/CreateDive.py
octodeco/deco/Cylinder.py
octodeco/deco/DivePoint.py
octodeco/deco/DiveProfile.py
octodeco/deco/DiveProfileSer.py
octodeco/deco/Gas.py
octodeco/deco/TissueStateCython.cp38-win_amd64.pyd
octodeco/deco/Util.py
octodeco/deco/__init__.py
octo_deco-2.0.3.dist-info/LICENSE.md
octo_deco-2.0.3.dist-info/METADATA
octo_deco-2.0.3.dist-info/WHEEL
octo_deco-2.0.3.dist-info/top_level.txt
octo_deco-2.0.3.dist-info/RECORD
