Metadata-Version: 2.1
Name: octo-deco
Version: 2.0.3
Summary: Package to do scuba diving decompression profile calculations, including web app
Home-page: https://octo-deco.nl/
Author: Dan Roozemond
Author-email: dan.roozemond@gmail.com
License: UNKNOWN
Project-URL: Source Code, https://github.com/danroozemond/octo-deco/
Platform: UNKNOWN
License-File: LICENSE.md
Requires-Dist: pandas
Requires-Dist: numpy
Requires-Dist: cython
